jsaxonpy/__init__.py
jsaxonpy/_version.py
jsaxonpy/jvm.py
jsaxonpy/singleton.py
jsaxonpy/xslt.py
jsaxonpy-0.7.2.dist-info/LICENSE
jsaxonpy-0.7.2.dist-info/METADATA
jsaxonpy-0.7.2.dist-info/WHEEL
jsaxonpy-0.7.2.dist-info/top_level.txt
jsaxonpy-0.7.2.dist-info/RECORD
