Metadata-Version: 2.1
Name: jsaxonpy
Version: 0.7.2
Summary: Java Saxon XSLT transformations in your python applications
Author-email: Andrey Kolotev <kolotev@gmail.com>
License: GNU GENERAL PUBLIC LICENSE
Project-URL: Home, https://github.com/kolotev/jsaxonpy
Project-URL: Source, https://github.com/kolotev/jsaxonpy
Classifier: License :: OSI Approved :: GNU General Public License v3 or later (GPLv3+)
Classifier: Intended Audience :: Developers
Classifier: Development Status :: 3 - Alpha
Classifier: Programming Language :: Python :: 3
Classifier: Programming Language :: Python :: 3.7
Classifier: Programming Language :: Python :: 3.8
Classifier: Programming Language :: Python :: 3.9
Classifier: Programming Language :: Python :: 3.10
Classifier: Programming Language :: Python :: 3.11
Classifier: Topic :: Software Development :: Libraries :: Python Modules
Classifier: Topic :: Software Development :: Libraries :: Java Libraries
Classifier: Topic :: Text Processing :: Markup :: XML
Classifier: Topic :: Software Development :: Libraries :: Java Libraries
Classifier: Operating System :: Unix
Requires-Python: >=3.7
License-File: LICENSE
Requires-Dist: pyjnius (<2.0.0,>=1.0.0)
Provides-Extra: dev
Requires-Dist: tox (>=4.0.0) ; extra == 'dev'
Requires-Dist: twine ; extra == 'dev'
Provides-Extra: test
Requires-Dist: pytest (>=7.2.0) ; extra == 'test'
Requires-Dist: pytest-xdist ; extra == 'test'
Requires-Dist: pytest-forked ; extra == 'test'
Requires-Dist: pytest-cov ; extra == 'test'
Requires-Dist: pytest-html ; extra == 'test'
Requires-Dist: hypothesis ; extra == 'test'
Requires-Dist: black ; extra == 'test'
Requires-Dist: isort ; extra == 'test'
Requires-Dist: flake8 ; extra == 'test'
